bincraft2json.cpython-312-x86_64-linux-gnu.so
bincraft2json/__init__.py
bincraft2json/bincraft2json.cpp
bincraft2json/bincraft2json.hpp
bincraft2json/bincraft2json.py
bincraft2json/bincraft2json_impl.hpp
bincraft2json/json.hpp
bincraft2json/setup.py
bincraft2json-0.1.4.dist-info/METADATA
bincraft2json-0.1.4.dist-info/WHEEL
bincraft2json-0.1.4.dist-info/top_level.txt
bincraft2json-0.1.4.dist-info/RECORD
