Metadata-Version: 2.4
Name: bincraft2json
Version: 0.1.4
Summary: Module Python to convert BinCraft files to JSON
Home-page: https://github.com/aymene69/bincraft2json
Author: Aymene69
Author-email: Aymene69 <belmegaming@gmail.com>
License: MIT
Project-URL: Homepage, https://github.com/aymene69/bincraft2json
Project-URL: Repository, https://github.com/aymene69/bincraft2json.git
Classifier: Development Status :: 4 - Beta
Classifier: Intended Audience :: Developers
Classifier: Operating System :: POSIX :: Linux
Classifier: Programming Language :: Python :: 3
Classifier: Programming Language :: Python :: 3.7
Classifier: Programming Language :: Python :: 3.8
Classifier: Programming Language :: Python :: 3.9
Classifier: Programming Language :: Python :: 3.10
Classifier: Programming Language :: Python :: 3.11
Classifier: Programming Language :: Python :: 3.12
Classifier: Programming Language :: C++
Classifier: Topic :: Software Development :: Libraries :: Python Modules
Requires-Python: >=3.7
Requires-Dist: pybind11>=2.6.0
Dynamic: author
Dynamic: home-page
Dynamic: requires-python
